{
  "n_compounds": 19696,
  "targets": [
    "AR",
    "BSEP",
    "CAR",
    "CYP1A2",
    "CYP2C19",
    "CYP2C9",
    "CYP2D6",
    "CYP3A4",
    "Cav1.2",
    "ER_beta",
    "ERa",
    "FXR",
    "GR",
    "LXRb",
    "MR",
    "Nav1.5",
    "P-gp",
    "PPARg",
    "PR",
    "PXR",
    "RXRa",
    "VDR",
    "hERG"
  ],
  "class_distribution": {
    "non_binding": 3144,
    "binding": 16552
  },
  "train_size": 11817,
  "val_size": 3939,
  "test_size": 3940,
  "best_model": "LightGBM",
  "top3_models": [
    "LightGBM",
    "XGBoost",
    "RandomForest"
  ],
  "model_selection_method": "MCDA composite (MCC-weighted, 40% MCC / 25% ROC-AUC / 20% PR-AUC)",
  "test_metrics": {
    "roc_auc_macro": 0.8894922751666938,
    "pr_auc_macro": 0.9720966604733531,
    "mcc": 0.48583159544489274,
    "ece": 0.2008173318177602,
    "mce": 0.9471147604282968
  },
  "conformal_coverage": 0.95,
  "avg_prediction_set_size": 1.2472081218274111,
  "out_of_domain_rate": 0.3520304568527919,
  "severe_ood_rate": 0.002284263959390863,
  "calibration_warning": 